<?xml version="1.0" encoding="UTF-8"?>
<objects serializationModel="Studio.01.08.00">
    <object class="EncodingSetting" id="{7845b660-294d-4e09-aa7f-bb3c68fefd35}">
        <property name="encodingFormat">
            <value>3</value>
        </property>
        <property name="quality">
            <value>37</value>
        </property>
        <relationship name="platform">
            <destination>{49b8852a-ffd5-4a92-bba8-de824d07c03b}</destination>
        </relationship>
        <relationship name="encodable">
            <destination>{1711027b-22c2-4d1b-b676-38df3d86cfa3}</destination>
        </relationship>
    </object>
</objects>
