<?xml version="1.0" encoding="UTF-8"?>
<objects serializationModel="Studio.01.08.00">
    <object class="Event" id="{699682ba-99f3-42be-8247-17f7c2238992}">
        <property name="name">
            <value>Thunder</value>
        </property>
        <property name="outputFormat">
            <value>2</value>
        </property>
        <relationship name="mixer">
            <destination>{fed1d7ee-3d7e-42da-8053-9b2202bdd88f}</destination>
        </relationship>
        <relationship name="masterTrack">
            <destination>{91a62ca5-2938-473d-9f3c-5e62f1d9c7df}</destination>
        </relationship>
        <relationship name="mixerInput">
            <destination>{f4781525-02dc-4e25-98d1-874f4c0f0a98}</destination>
        </relationship>
        <relationship name="automatableProperties">
            <destination>{9b20f28c-cac8-44f2-937e-9c67874992b4}</destination>
        </relationship>
        <relationship name="markerTracks">
            <destination>{d10eb4f2-4a78-4f7b-89c2-79852a0719f4}</destination>
        </relationship>
        <relationship name="groupTracks">
            <destination>{c674fa93-0d96-496c-b653-209b660edbb3}</destination>
        </relationship>
        <relationship name="timeline">
            <destination>{c0130da3-1159-4183-a692-596a53b17340}</destination>
        </relationship>
        <relationship name="banks">
            <destination>{53bdd872-28a3-427d-8e18-8e20d1115aa9}</destination>
        </relationship>
        <relationship name="folder">
            <destination>{444f6f77-7602-455d-8f41-bbeabfb624d0}</destination>
        </relationship>
    </object>
    <object class="EventMixer" id="{fed1d7ee-3d7e-42da-8053-9b2202bdd88f}">
        <relationship name="masterBus">
            <destination>{ff2be148-230a-468c-aab9-1b89bfaa1d73}</destination>
        </relationship>
    </object>
    <object class="MasterTrack" id="{91a62ca5-2938-473d-9f3c-5e62f1d9c7df}">
        <relationship name="mixerGroup">
            <destination>{ff2be148-230a-468c-aab9-1b89bfaa1d73}</destination>
        </relationship>
    </object>
    <object class="MixerInput" id="{f4781525-02dc-4e25-98d1-874f4c0f0a98}">
        <relationship name="effectChain">
            <destination>{511da2f5-9120-4f5a-b2e2-1f2175021e09}</destination>
        </relationship>
        <relationship name="panner">
            <destination>{d5356a1c-12c3-4bbb-a006-36786777addb}</destination>
        </relationship>
        <relationship name="output">
            <destination>{95391962-d012-4920-a7a5-e6bb67034b49}</destination>
        </relationship>
    </object>
    <object class="EventAutomatableProperties" id="{9b20f28c-cac8-44f2-937e-9c67874992b4}"/>
    <object class="MarkerTrack" id="{d10eb4f2-4a78-4f7b-89c2-79852a0719f4}"/>
    <object class="GroupTrack" id="{c674fa93-0d96-496c-b653-209b660edbb3}">
        <relationship name="mixerGroup">
            <destination>{d2071156-d0d2-4d56-8d48-54e170fb217a}</destination>
        </relationship>
    </object>
    <object class="Timeline" id="{c0130da3-1159-4183-a692-596a53b17340}"/>
    <object class="EventMixerMaster" id="{ff2be148-230a-468c-aab9-1b89bfaa1d73}">
        <relationship name="effectChain">
            <destination>{1059adf9-8ae6-4762-83f9-033f9521d21b}</destination>
        </relationship>
        <relationship name="panner">
            <destination>{9274bbc3-33c4-4f81-b3d6-e6f65f95712d}</destination>
        </relationship>
        <relationship name="mixer">
            <destination>{fed1d7ee-3d7e-42da-8053-9b2202bdd88f}</destination>
        </relationship>
    </object>
    <object class="MixerBusEffectChain" id="{511da2f5-9120-4f5a-b2e2-1f2175021e09}">
        <relationship name="effects">
            <destination>{978ea363-f4cc-4295-94d9-078839ff5b3c}</destination>
        </relationship>
    </object>
    <object class="MixerBusPanner" id="{d5356a1c-12c3-4bbb-a006-36786777addb}"/>
    <object class="EventMixerGroup" id="{d2071156-d0d2-4d56-8d48-54e170fb217a}">
        <property name="name">
            <value>Audio 1</value>
        </property>
        <relationship name="effectChain">
            <destination>{bce9c757-ff30-4352-81a9-0a02dfe893cc}</destination>
        </relationship>
        <relationship name="panner">
            <destination>{92bb04dd-88de-4b55-8377-4e4c345b8e1c}</destination>
        </relationship>
        <relationship name="output">
            <destination>{ff2be148-230a-468c-aab9-1b89bfaa1d73}</destination>
        </relationship>
    </object>
    <object class="MixerBusEffectChain" id="{1059adf9-8ae6-4762-83f9-033f9521d21b}">
        <relationship name="effects">
            <destination>{1a078591-8230-4686-84cb-6aaff0d3cffa}</destination>
            <destination>{714aca7c-935f-462d-9fb8-818ee7541de9}</destination>
            <destination>{2e3c9309-fa06-4337-93a9-22e5b7ea8eac}</destination>
        </relationship>
    </object>
    <object class="MixerBusPanner" id="{9274bbc3-33c4-4f81-b3d6-e6f65f95712d}"/>
    <object class="MixerBusFader" id="{978ea363-f4cc-4295-94d9-078839ff5b3c}"/>
    <object class="MixerBusEffectChain" id="{bce9c757-ff30-4352-81a9-0a02dfe893cc}">
        <relationship name="effects">
            <destination>{d069c74c-b1f6-4522-9857-66100e041f31}</destination>
        </relationship>
    </object>
    <object class="MixerBusPanner" id="{92bb04dd-88de-4b55-8377-4e4c345b8e1c}"/>
    <object class="MixerBusFader" id="{1a078591-8230-4686-84cb-6aaff0d3cffa}"/>
    <object class="SpatialiserEffect" id="{714aca7c-935f-462d-9fb8-818ee7541de9}"/>
    <object class="MixerSend" id="{2e3c9309-fa06-4337-93a9-22e5b7ea8eac}">
        <property name="inputFormat">
            <value>2</value>
        </property>
        <relationship name="mixerReturn">
            <destination>{2aa29a42-0f6e-405d-96f5-24503a259acd}</destination>
        </relationship>
    </object>
    <object class="MixerBusFader" id="{d069c74c-b1f6-4522-9857-66100e041f31}"/>
</objects>
